LICENSE.txt
MANIFEST.in
README.md
requirements.txt
setup.cfg
setup.py
cgbeacon/__init__.py
cgbeacon/__version__.py
cgbeacon.egg-info/PKG-INFO
cgbeacon.egg-info/SOURCES.txt
cgbeacon.egg-info/dependency_links.txt
cgbeacon.egg-info/entry_points.txt
cgbeacon.egg-info/requires.txt
cgbeacon.egg-info/top_level.txt
cgbeacon/cli/__init__.py
cgbeacon/cli/root.py
cgbeacon/utils/Utility.py
cgbeacon/utils/__init__.py
cgbeacon/utils/mysql_handler.py
cgbeacon/utils/pdf_report_writer.py
cgbeacon/utils/vcf_panel_filter.py
cgbeacon/utils/vcfparser.py