Metadata-Version: 1.1
Name: cgbeacon
Version: 0.3.0
Summary: Extracts variants from a VCF file and inserts them into a Beacon MySQL database
Home-page: https://github.com/Clinical-Genomics/cgbeacon
Author: Chiara Rasi
Author-email: chiara.rasi@scilifelab.se
License: MIT
Download-URL: https://github.com/Clinical-Genomics/cgbeacon/tarball/0.3.0
Keywords: Genetic variants,VCF,sequencing,mutations,beacon
Platform: UNKNOWN
Classifier: License :: OSI Approved :: MIT License
Classifier: Programming Language :: Python
Classifier: Programming Language :: Python :: 2.6
Classifier: Programming Language :: Python :: 2.7
Classifier: Programming Language :: Python :: 3
Classifier: Programming Language :: Python :: 3.3
Classifier: Programming Language :: Python :: 3.4
Classifier: Programming Language :: Python :: 3.5
Classifier: Programming Language :: Python :: 3.6
Classifier: Programming Language :: Python :: Implementation :: CPython
Classifier: Programming Language :: Python :: Implementation :: PyPy
Classifier: Intended Audience :: Science/Research
Classifier: Operating System :: MacOS
Classifier: Operating System :: Unix
